funcfactory/__init__.py
funcfactory/core.py
funcfactory/decorators.py
funcfactory/enums.py
funcfactory/utils.py
funcfactory-0.1.6.dist-info/LICENSE.txt
funcfactory-0.1.6.dist-info/METADATA
funcfactory-0.1.6.dist-info/WHEEL
funcfactory-0.1.6.dist-info/top_level.txt
funcfactory-0.1.6.dist-info/RECORD
