Metadata-Version: 2.1
Name: funcfactory
Version: 0.1.6
Summary: Python package The FuncFactory! Easily adaptable production grade code on the fly.
Home-page: https://github.com/szindel/FuncFactory
Author: Steven Zindel
Author-email: steven.zindel@gmail.com
License: Apache 2.0
Download-URL: https://github.com/user/reponame/archive/v_01.tar.gz
Keywords: FuncFactory,Functions,Production Code
Platform: UNKNOWN
Classifier: Development Status :: 3 - Alpha
Classifier: Intended Audience :: Developers
Classifier: Topic :: Software Development :: Build Tools
Classifier: License :: OSI Approved :: MIT License
Classifier: Programming Language :: Python :: 3
Classifier: Programming Language :: Python :: 3.7
Classifier: Programming Language :: Python :: 3.8
Classifier: Programming Language :: Python :: 3.9
Requires-Python: >=3.7
License-File: LICENSE.txt
